dlearn/__init__.py
dlearn-0.1.0.dist-info/DESCRIPTION.rst
dlearn-0.1.0.dist-info/METADATA
dlearn-0.1.0.dist-info/RECORD
dlearn-0.1.0.dist-info/WHEEL
dlearn-0.1.0.dist-info/metadata.json
dlearn-0.1.0.dist-info/top_level.txt
