Metadata-Version: 2.0
Name: dlearn
Version: 0.1.0
Summary: A collection of python modules for machine learning.
Home-page: https://github.com/de-eplearn/dlearn
Author: Dirk Elsinghorst
Author-email: de.eplearn5@gmail.com
License: MIT
Keywords: machine learning preprocessing cluster
Platform: UNKNOWN
Classifier: Development Status :: 1 - Planning
Classifier: License :: OSI Approved :: MIT License
Classifier: Programming Language :: Python :: 3.6
Classifier: Topic :: Scientific/Engineering :: Artificial Intelligence
Requires-Dist: numpy
Requires-Dist: sklearn
